[
	{
		"id":"3101001",
		"ref_03":"3101002",
		
		"dist_03":73.5,
		
		"lat" : 40.713608846195484,
		"lng" : -73.6039129715515,

		"stru_00":"CMCTR00"
	},
	
	{
		"id":"3101002",
		"ref_03":"3101001",
		"ref_04":"3001001",
		"ref_05":"3101003",
		
		"dist_03":73.5,
		"dist_04":42,
		"dist_05":55.1,
		
        "lat" : 40.71390892650545,
		"lng" : -73.60347200879124
	},
	
	{
		"id":"3101003",
		"ref_03":"3101002",
		"ref_04":"3101004",
		
		"dist_03":55.1,
		"dist_04":25,
		
        "lat" : 40.71405937204249,
		"lng" : -73.60283632525471,
        
		"stru_00":"BERN00"
	},
	
    {
		"id":"3101004",
		"ref_03":"3101003",
		"ref_04":"3002001",
		
		"dist_03":25,
		"dist_04":30,
		
        "lat" : 40.71415960448217,
		"lng" : -73.60251972706783
	},
    
	{
		"id":"3102001",
		"ref_03":"3102002",
        "ref_04":"3002001",
		
		"dist_03":26.3,
        "dist_04":45,
		
        "lat" : 40.71409580149151,
		"lng" : -73.6019324208167,
        
		"stru_00":"MEML01"
	},
	
	{
		"id":"3102002",
		"ref_03":"3102001",
		"ref_04":"3102003",
		"ref_05":"3103002",
		"ref_06":"3103001",
		
		"dist_03":26.3,
		"dist_04":39.4,
		"dist_05":47.3,
		"dist_06":23.6,
		
        "lat" : 40.714173835777736,
		"lng" : -73.60169092448223,
        
		"stru_00":"HAUSR00"
	},
	
	{
		"id":"3102003",
		"ref_03":"3102002",
		"ref_04":"3102004",
		
		"dist_03":39.4,
		"dist_04":15.8,
		
        "lat" : 40.71427548780042,
		"lng" : -73.60144282014835,
        
		"stru_00":"HAUSR00"
	},
	
	{
		"id":"3102004",
		"ref_03":"3102003",
		"ref_04":"3103002",
		
		"dist_03":15.8,
		"dist_04":23.6,
        
        "lat" : 40.714326313753546,
		"lng" : -73.60131005080211
	},
	
	{
		"id":"3103001",
		"ref_03":"3103002",
		"ref_04":"3104002",
		"ref_05":"3004001",
		
		"dist_03":23.6,
		"dist_04":36.8,
		"dist_05":42,
		
        "lat" : 40.71401424178908,
		"lng" : -73.60158095391262,
		
		"stru_00":"MEML00"
	},
	
	{
		"id":"3103002",
		"ref_03":"3103001",
		"ref_04":"3102002",
		"ref_05":"3102004",
		"ref_06":"3103003",
		"ref_07":"310600a",
		"ref_08":"3004001",
		
		
		"dist_03":36.8,
		"dist_04":47.3,
		"dist_05":23.6,
		"dist_06":26.3,
		"dist_07":52.5,
		"dist_08":52.5,
        
        "lat" : 40.7141555383972,
		"lng" : -73.6011638704108
		
	},
	
	{
		"id":"3103003",
		"ref_03":"3103002",
		"ref_04":"3103004",
		"ref_05":"3104001",
		
		"dist_03":26.3,
		"dist_04":36.8,
		"dist_05":18.4,
        
        "lat" : 40.71424397569,
		"lng" : -73.60086661697989
	},
	
	{
		"id":"3103004",
		"ref_03":"3103003",
		"ref_04":"3008001",
		"ref_05":"3103005",
		"ref_06":"3104003",
		
		"dist_03":36.8,
		"dist_04":42,
		"dist_05":34.1,
		"dist_06":21,
        
        "lat" : 40.7143775590381,
		"lng" : -73.60049031989354
	},
	
	{
		"id":"3103005",
		"ref_03":"3103004",
		"ref_04":"3201001",
		"ref_05":"3103006",
		"ref_06":"3104003",
		
		"dist_03":34.1,
		"dist_04":36.8,
		"dist_05":18.4,
		"dist_06":39.4,
        
        "lat" : 40.71445786390316,
		"lng" : -73.60024757997769
	},
	
	{
		"id":"3103006",
		"ref_03":"3103005",
		"ref_04":"3201001",
		"ref_05":"3103007",
		"ref_06":"310600d",
		
		"dist_03":18.4,
		"dist_04":26.3,
		"dist_05":21,
		"dist_06":49.9,
        
        "lat" : 40.71454223473298,
		"lng" : -73.59986402408856
		
	},
	
	{
		"id":"3103007",
		"ref_03":"3103006",
		"ref_04":"3201002",
		"ref_05":"3103008",
		"ref_06":"310600f",
		
		"dist_03":21,
		"dist_04":28.9,
		"dist_05":13.1,
		"dist_06":47.3,
        
        "lat" : 40.71463168802614,
		"lng" : -73.59961524920243
	},
	
	{
		"id":"3103008",
		"ref_03":"3103007",
		"ref_04":"3103009",
		
		"dist_03":13.1,
		"dist_04":34.1,
        
        "lat" : 40.714676992863424,
		"lng" : -73.59950079371248,
		
		"stru_00":"MASON00",
	},
	
	{
		"id":"3103009",
		"ref_03":"3103008",
		"ref_04":"300b001",
		"ref_05":"3106011",
		
		"dist_03":34.1,
		"dist_04":89.3,
		"dist_05":52.5,
        
        "lat" : 40.714844849956734,
		"lng" : -73.59906179600472
	},
	
	{
		"id":"3104001",
		"ref_03":"3103003",
		"ref_04":"3104002",
		"ref_05":"3007001",
		
		"dist_03":18.4,
		"dist_04":28.9,
		"dist_05":15.8,
        
        "lat" : 40.71408034168283,
		"lng" : -73.60077208515293,
		
		"stru_00":"DAVN00"
	},
	
	{
		"id":"3104002",
		"ref_03":"3104001",
		"ref_04":"3104003",
		
		"dist_03":28.9,
		"dist_04":23.6,
		
        "lat" : 40.71418097732736,
		"lng" : -73.60048777099735,
        
		"stru_00":"HOFSHL00"
	},
	
	{
		"id":"3104003",
		"ref_03":"3104002",
		"ref_04":"3103004",
		"ref_05":"3103005",
		"ref_06":"3008002",
		
		"dist_03":23.6,
		"dist_04":21,
		"dist_05":39.4,
		"dist_06":15.8,
        
        "lat" : 40.71425721635072,
		"lng" : -73.60022491451389,
		
		"stru_00":"PHLPS00"
	},
    
    {
		"id":"3105001",
		"ref_03":"3106000",
		"ref_04":"3105002",
		
		"dist_03":40.4,
		"dist_04":15.8,
		
        "lat" : 40.7132415313667,
		"lng" : -73.60319269524484
	},
	
	{
		"id":"3105002",
		"ref_03":"3105001",
		"ref_04":"3105003",
		
		"dist_03":15.8,
		"dist_04":15.8,
		
        "lat" : 40.71328829197119,
		"lng" : -73.60305590258508,
        
		"stru_00":"WEED00"
	},
	
	{
		"id":"3105003",
		"ref_03":"3105002",
		"ref_04":"3005004",
		"ref_05":"3106003",
		
		"dist_03":15.8,
		"dist_04":70,
		"dist_05":36.8,
        
        "lat" : 40.71335538321589,
		"lng" : -73.602860101327
	},
    
    {
		"id":"3105004",
		"ref_03":"3105003",
		"ref_04":"3002001",
		"ref_05":"3106006",
		
		"dist_03":70,
		"dist_04":23,
		"dist_05":35,
        
        "lat" : 40.713554623483496,
		"lng" : -73.60210774169832
	},
	
    {  
		"id":"3106000",
		"ref_03":"3105001",
		"ref_04":"3106001",
		
		"dist_03":40.4,
		"dist_04":6,
        
        "lat" : 40.71291725583656,
		"lng" : -73.6030947946158,
	},
    
	{
		"id":"3106001",
		"ref_03":"3106000",
		"ref_04":"3106002",
		
		"dist_03":6,
		"dist_04":21,
        
        "lat" : 40.7129426693364,
		"lng" : -73.60301701055437,
		
		"stru_00":"WEED00"
	},
	
	{
		"id":"3106002",
		"ref_03":"3106001",
		"ref_04":"3106003",
		
		"dist_03":21,
		"dist_04":23.6,
        
        "lat" : 40.71301890977773,
		"lng" : -73.60280243383318,
		
		"stru_00":"WEED00"
	},
	
	{
		"id":"3106003",
		"ref_03":"3106002",
		"ref_04":"3105003",
		"ref_05":"3106003",
		
		"dist_03":23.6,
		"dist_04":36.8,
		"dist_05":13.1,
        
        "lat" : 40.713110398192086,
		"lng" : -73.6025355540362
	},
	
	{
		"id":"3106004",
		"ref_03":"3106003",
		"ref_04":"3106005",
		
		"dist_03":13.1,
		"dist_04":18.4,
        
        "lat" : 40.7131480100593,
		"lng" : -73.60243765340715,
		
		"stru_00":"ADAM00"
	},
	
	{
		"id":"3106005",
		"ref_03":"3106004",
		"ref_04":"3106006",
		
		"dist_03":18.4,
		"dist_04":21,
        
        "lat" : 40.71322425026549,
		"lng" : -73.60222844110399,
		
		"stru_00":"ADAM00"
	},
	
	{
		"id":"3106006",
		"ref_03":"3106005",
		"ref_04":"3005004",
		"ref_05":"3106007",
		"ref_06":"3108001",
		
		"dist_03":21,
		"dist_04":35,
		"dist_05":21,
		"dist_06":52.5,
        
        "lat" : 40.71331573839767,
		"lng" : -73.60196692572504
	},
	
	{
		"id":"3106007",
		"ref_03":"3106006",
		"ref_04":"3106008",
		"ref_05":"3003001",
		
		"dist_03":21,
		"dist_04":18.4,
		"dist_05":26.3,
        
        "lat" : 40.713356399749415,
		"lng" : -73.60185024963289
	},
	
	{
		"id":"3106008",
		"ref_03":"3106007",
		"ref_04":"3106009",
		
		"dist_03":18.4,
		"dist_04":31.5,
        
        "lat" : 40.713447465130194,
		"lng" : -73.6016022984262,
		
		"stru_00":"MEML00",
		"stru_01":"LOWE00",
	},
	
	{
		"id":"3106009",
		"ref_03":"3106008",
		"ref_04":"3004001",
		"ref_05":"310600a",
		"ref_06":"3108004",
		
		"dist_03":31.5,
		"dist_04":18.4,
		"dist_05":36.8,
		"dist_06":52.5,
        
        "lat" : 40.71356030009688,
		"lng" : -73.60128847997146
	},
	
	{
		"id":"310600a",
		"ref_03":"3106009",
		"ref_04":"3004001",
		"ref_05":"3103002",
		"ref_06":"310600b",
		"ref_07":"3108006",
		
		"dist_03":36.8,
		"dist_04":39.4,
		"dist_05":52.5,
		"dist_06":26.3,
		"dist_07":49.9,
        
        "lat" : 40.71369085297133,
		"lng" : -73.60090358297782
	},
	
	{
		"id":"310600b",
		"ref_03":"310600a",
		"ref_04":"3007001",
		"ref_05":"310600c",
		"ref_06":"3007002",
		
		"dist_03":26.3,
		"dist_04":21,
		"dist_05":52.5,
		"dist_06":26.3,
        
        "lat" : 40.71379962141883,
		"lng" : -73.60061278151193
	},
	
	{
		"id":"310600c",
		"ref_03":"310600b",
		"ref_04":"3008002",
		"ref_05":"310600d",
		"ref_06":"3008003",
		
		"dist_03":52.5,
		"dist_04":21,
		"dist_05":36.8,
		"dist_06":26.3,
        
        "lat" : 40.7140008934044,
		"lng" : -73.60006561087289
	},
	
	{
		"id":"310600d",
		"ref_03":"310600c",
		"ref_04":"3103006",
		"ref_05":"310600e",
		"ref_06":"3107001",
		
		"dist_03":36.8,
		"dist_04":49.9,
		"dist_05":21,
		"dist_06":18.4,
        
        "lat" : 40.71412999178191,
		"lng" : -73.59969680713334
	},
	
	{
		"id":"310600e",
		"ref_03":"310600d",
		"ref_04":"310600f",
		"ref_05":"3107002",
		
		"dist_03":21,
		"dist_04":7.9,
		"dist_05":15.8,
        
        "lat" : 40.714181024579155,
		"lng" : -73.59955196784654
	},
	
    
	{
		"id":"310600f",
		"ref_03":"310600e",
		"ref_04":"3103007",
		"ref_05":"3106010",
		
		
		"dist_03":7.9,
		"dist_04":47.3,
		"dist_05":13.1,
        
        "lat" : 40.71424913144415,
		"lng" : -73.59938164757409
	},
	
	{
		"id":"3106010",
		"ref_03":"310600f",
		"ref_04":"3106011",
		
		"dist_03":13.1,
		"dist_04":23.6,
        
        "lat" : 40.71428877570662,
		"lng" : -73.5992569248549,
		
		"stru_00":"MASON00",
		"stru_01":"SPIEG00"
	},
	
	{
		"id":"3106011",
		"ref_03":"3106010",
		"ref_04":"3103009",
		"ref_05":"3107003",
		
		"dist_03":23.6,
		"dist_04":52.5,
		"dist_05":15.8,
        
        "lat" : 40.71437314675072,
		"lng" : -73.59896724628129
	},
	
	{
		"id":"3107001",
		"ref_03":"3108009",
		"ref_04":"310600d",
		"ref_05":"3107002",
		
		"dist_03":36.8,
		"dist_04":18.4,
		"dist_05":21,
        
        "lat" : 40.71399828064738,
		"lng" : -73.59961798551348
	},
	
	{
		"id":"3107002",
		"ref_03":"3107001",
		"ref_04":"310600e",
		"ref_05":"3107003",
		
		"dist_03":21,
		"dist_04":15.8,
		"dist_05":42,
        
        "lat" : 40.7140521563808,
		"lng" : -73.59946509959963
	},
	
	{
		"id":"3107003",
		"ref_03":"3107002",
		"ref_04":"3106011",
		"ref_05":"310800a",
		
		"dist_03":42,
		"dist_04":15.8,
		"dist_05":36.8,
        
        "lat" : 40.71423959384847,
		"lng" : -73.59894597602153
	},
	
	{
		"id":"3108001",
		"ref_03":"3106006",
		"ref_04":"3108002",
		
		"dist_03":52.5,
		"dist_04":23.6,
        
        "lat" : 40.71289141267897,
		"lng" : -73.60178035394478,
				
		"stru_00":"SHAPR"
	},
	
	{
		"id":"3108002",
		"ref_03":"3108001",
		"ref_04":"3003001",
		"ref_05":"3108003",
		"ref_06":"310a001",
		
		"dist_03":23.6,
		"dist_04":26.3,
		"dist_05":23.6,
		"dist_06":99.8,
        
        "lat" : 40.71295373173921,
		"lng" : -73.60157434669924
	},
	
	{
		"id":"3108003",
		"ref_03":"3108002",
		"ref_04":"3108004",
		
		"dist_03":23.6,
		"dist_04":23.6,
        
        "lat" : 40.7130655510047,
		"lng" : -73.60125918713999,
		
		"stru_00":"LOWE00"
	},
	
	{
		"id":"3108004",
		"ref_03":"3108003",
		"ref_04":"3106009",
		"ref_05":"3108005",
		
		"dist_03":23.6,
		"dist_04":52.5,
		"dist_05":39.4,
        
        "lat" : 40.71314280784208,
		"lng" : -73.60103924600077
	},
	
	{
		"id":"3108005",
		"ref_03":"3108004",
		"ref_04":"3108006",
		
		"dist_03":39.4,
		"dist_04":21,
        
        "lat" : 40.7132098992334,
		"lng" : -73.60085283247423,
		
		"stru_00":"PLYHS00"
	},
	
	{
		"id":"3108006",
		"ref_03":"3108005",
		"ref_04":"310600a",
		"ref_05":"3108007",
		"ref_06":"3006001",
		
		"dist_03":21,
		"dist_04":49.9,
		"dist_05":23.6,
		"dist_06":28.9,
        
        "lat" : 40.71330443698821,
		"lng" : -73.60058461157274
	},
	
	{
		"id":"3108007",
		"ref_03":"3108006",
		"ref_04":"3007002",
		"ref_05":"3108008",
		
		"dist_03":23.6,
		"dist_04":26.3,
		"dist_05":52.5,
        
        "lat" : 40.713383726614566,
		"lng" : -73.60037539926958,
		
		"stru_00":"CALK00"
	},
	
	{
		"id":"3108008",
		"ref_03":"3108007",
		"ref_04":"3008003",
		"ref_05":"3108009",
		
		"dist_03":52.5,
		"dist_04":26.3,
		"dist_05":26.3,
        
        "lat" : 40.713563263096404,
		"lng" : -73.59981978000667,
		
		"stru_00":"CALK00"
	},
	
	{
		"id":"3108009",
		"ref_03":"3108008",
		"ref_04":"3107001",
		"ref_05":"310800a",
		"ref_06":"3109003",
		
		"dist_03":26.3,
		"dist_04":36.8,
		"dist_05":52.5,
		"dist_06":45,
        
        "lat" : 40.71366186646488,
		"lng" : -73.59959849776294
	},
	
	{
		"id":"310800a",
		"ref_03":"3108009",
		"ref_04":"3107003",
		"ref_05":"3109003",
		
		"dist_03":52.5,
		"dist_04":36.8,
		"dist_05":39.4,
        
        "lat" : 40.713896684208045,
		"lng" : -73.59889978231456
	},
	
	{
		"id":"3109001",
		"ref_03":"3006001",
		"ref_06":"3109002",
		"ref_07":"3006002",
		
		"dist_03":18.4,
		"dist_06":78.5,
		"dist_07":36.8,
        
        "lat" : 40.71292076468003,
		"lng" : -73.60039659470146,
		
		"stru_00":"DUNKN00"
	},
    
    {
		"id":"3109002",
		"ref_03":"3109001",
		"ref_04":"3109003",
        "ref_05":"3009001",
		
		"dist_03":78.5,
		"dist_04":20,
        "dist_05":15.8,
        
        "lat" : 40.713155158191725,
		"lng" : -73.59952207177372
	},
    
    {
		"id":"3109003",
		"ref_03":"3109002",
        "ref_04":"3108009",
		"ref_04":"3109004",
		
		"dist_03":20,
		"dist_04":15.8,
        "dist_05":45,
        
        "lat" : 40.71340014305089,
		"lng" : -73.59929274290295
	},
	
	{
		"id":"3109004",
		"ref_03":"3109003",
		"ref_04":"3109005",
		
		"dist_03":15.8,
		"dist_04":23.6,
        
        "lat" : 40.71341132491093,
		"lng" : -73.59911571710796,
		
		"stru_00":"WELLR00"
	},
	
	{
		"id":"3109005",
		"ref_03":"3109004",
		"ref_04":"310800a",
		"ref_05":"310a00a",
		
		"dist_03":23.6,
		"dist_04":39.4,
		"dist_05":47.3,
        
        "lat" : 40.71349874666096,
		"lng" : -73.59885420172901
	},
	
	{
		"id":"310a001",
		"ref_03":"3108002",
		"ref_04":"310a002",
		
		"dist_03":99.8,
		"dist_04":21,
        
        "lat" : 40.71208341040764,
		"lng" : -73.60105788537771
	},
	
	{
		"id":"310a002",
		"ref_03":"310a001",
		"ref_04":"310a003",
		
		"dist_03":21,
		"dist_04":23.6,
        
        "lat" : 40.7121901483785,
		"lng" : -73.60083257982046,
		
		"stru_00":"BRESL00"
	},
	
	{
		"id":"310a003",
		"ref_03":"310a002",
		"ref_04":"310a004",
		"ref_05":"3005001",
		
		"dist_03":23.6,
		"dist_04":21,
		"dist_05":21,
        
        "lat" : 40.71232738266103,
		"lng" : -73.60067567059309,
		
		"stru_00":"CMCTR00"
	},
	
	{
		"id":"310a004",
		"ref_03":"310a003",
		"ref_04":"310a005",
		"ref_05":"3005001",
		
		"dist_03":21,
		"dist_04":26.3,
		"dist_05":23.6,
        
        "lat" : 40.71241553620016,
		"lng" : -73.60047938755883
	},
	
	{
		"id":"310a005",
		"ref_03":"310a004",
		"ref_04":"3006002",
		"ref_05":"310a006",
		"ref_06":"310b001",
		
		"dist_03":26.3,
		"dist_04":21,
		"dist_05":36.8,
		"dist_06":44.6,
        
        "lat" : 40.71250397580416,
		"lng" : -73.60018836788072
	},
	
	{
		"id":"310a006",
		"ref_03":"310a005",
		"ref_04":"310a007",
		"ref_05":"310b001",
		
		"dist_03":36.8,
		"dist_04":26.3,
		"dist_05":44.6,
        
        "lat" : 40.712658490692505,
		"lng" : -73.59972032240762,
		
		"stru_00":"RSVLT00"
	},
	
	{
		"id":"310a007",
		"ref_03":"310a006",
		"ref_04":"310a008",
		
		"dist_03":26.3,
		"dist_04":18.4,
        
        "lat" : 40.712738797631005,
		"lng" : -73.59947892359628,
		
		"stru_00":"RSVLT00"
	},
	
	{
		"id":"310a008",
		"ref_03":"310a007",
		"ref_04":"3009001",
		"ref_05":"310a009",
		"ref_06":"310b004",
		
		"dist_03":18.4,
		"dist_04":28.9,
		"dist_05":21,
		"dist_06":52.5,
        
        "lat" : 40.71278962475722,
		"lng" : -73.5993032389058
	},
	
	{
		"id":"310a009",
		"ref_03":"310a008",
		"ref_04":"310a00a",
		
		"dist_03":21,
		"dist_04":23.6,
        
        "lat" : 40.7129634532356,
		"lng" : -73.59916778735055,
		
		"stru_00":"AUBPN00"
	},
	
	{
		"id":"310a00a",
		"ref_03":"310a009",
		"ref_04":"3109003",
		"ref_05":"310c004",
		
		"dist_03":23.6,
		"dist_04":47.3,
		"dist_05":186.4,
        
        "lat" : 40.713104752073725,
		"lng" : -73.59877618483438,
		
		"stru_00":"AUBPN00"
	},
	
	{
		"id":"310b001",
		"ref_03":"310a005",
		"ref_04":"310a006",
		"ref_05":"310b002",
		
		"dist_03":44.6,
		"dist_04":44.6,
		"dist_05":18.4,
        
        "lat" : 40.71235657639896,
		"lng" : -73.59980078867807,
		
		"stru_00":"KUSHN00",
		"stru_01":"KOPPL00"
	},
	
	{
		"id":"310b002",
		"ref_03":"310b001",
		"ref_04":"310b003",
		"ref_05":"300a001",
		
		"dist_03":18.4,
		"dist_04":23.6,
		"dist_05":31.5,
        
        "lat" : 40.71239622178832,
		"lng" : -73.5996438794507
	},
	
	{
		"id":"310b003",
		"ref_03":"310b002",
		"ref_04":"310b004",
		"ref_05":"300a001",
		
		"dist_03":23.6,
		"dist_04":7.9,
		"dist_05":31.5,
        
        "lat" : 40.71247347940233,
		"lng" : -73.59941723278894
	},
	
	{
		"id":"310b004",
		"ref_03":"310b003",
		"ref_04":"310a008",
		
		"dist_03":7.9,
		"dist_04":52.5,
        
        "lat" : 40.71256496856612,
		"lng" : -73.59917181066407,
		
		"stru_00":"RSVLT00"
	},
	
	{
		"id":"310c001",
		"ref_03":"310c002",
		
		"dist_03":26.3,
        
        "lat" : 40.71171486674682,
		"lng" : -73.60038785298696,
		
		"stru_00":"BRESL00"
	},
	
	{
		"id":"310c002",
        "ref_03":"310c001",
		"ref_04":"3005003",
		"ref_05":"310c003",
		
        "dist_03":26.3,
		"dist_04":39.4,
		"dist_05":42,
        
        "lat" : 40.71180320833284,
		"lng" : -73.60009527463916
	},
    
    {
		"id":"310c003",
		"ref_03":"310c002",
		"ref_04":"310c004",
		
		"dist_03":42,
		"dist_04":34.1,
        
        "lat" : 40.71156759228989,
		"lng" : -73.599754368145,
		
		"stru_00":"KOPPL00"
	},
	
	{
		"id":"310c004",
		"ref_03":"310c003",
		"ref_04":"310c005",
		
		"dist_03":34.1,
		"dist_04":40,
        
        "lat" : 40.71156759228989,
		"lng" : -73.599754368145,
		
		"stru_00":"KOPPL00"
	},
	
	{
		"id":"310c005",
		"ref_03":"310c004",
		"ref_04":"300a002",
		"ref_05":"310a00a",
		
		"dist_03":40,
		"dist_04":30,
		"dist_05":186.4,
        
        "lat" : 40.71160622158884,
		"lng" : -73.5985849250145,
	},
	
	{
		"id":"3201001",
		"ref_03":"3103005",
		"ref_04":"3201002",
		"ref_05":"3103006",
		
		"dist_03":36.8,
		"dist_04":26.3,
		"dist_05":26.3,
        
        "lat" : 40.71478723412372,
		"lng" : -73.60001729303866,
		
		"stru_00":"HEGER00"
	},
	
	{
		"id":"3201002",
		"ref_03":"3201001",
		"ref_04":"3201003",
		"ref_05":"3103007",
		
		"dist_03":26.3,
		"dist_04":13.1,
		"dist_05":28.9,
        
        "lat" : 40.714879736618435,
		"lng" : -73.59976248318225,
		
		"stru_00":"HEGER00"
	},
	
	{
		"id":"3201003",
		"ref_03":"3201002",
		"ref_04":"3103009",
		
		"dist_03":78.8,
		"dist_04":89.3,
        
        "lat" : 40.71564044906913,
		"lng" : -73.59926333279009
	}
]